AmpliPy-1.1.dist-info/DESCRIPTION.rst
AmpliPy-1.1.dist-info/METADATA
AmpliPy-1.1.dist-info/RECORD
AmpliPy-1.1.dist-info/WHEEL
AmpliPy-1.1.dist-info/entry_points.txt
AmpliPy-1.1.dist-info/metadata.json
AmpliPy-1.1.dist-info/top_level.txt
amplipy/__init__.py
amplipy/amplipy-test.py
amplipy/amplipy.py
amplipy/console.py
