Metadata-Version: 2.0
Name: AmpliPy
Version: 1.1
Summary: A Python preprocessor
Home-page: http://github.com/orangeflash81/amplipy
Author: UNKNOWN
Author-email: UNKNOWN
License: MIT
Keywords: preprocessor,lambda,amplipy
Platform: UNKNOWN
Requires-Dist: astor
Requires-Dist: colorama
Requires-Dist: sphinx
